{
  "metadata": {
    "parsed_at": "2025-09-16T08:44:49.715549",
    "total_groups": 5,
    "source": "하남",
    "has_actual_links": true,
    "has_naver_map_urls": true,
    "has_kakao_reviews": true,
    "has_kakao_map_urls": true
  },
  "data": [
    {
      "name": "하남양곱창 본점",
      "location": "경기 하남시 신장로154번길 69 1층",
      "link": "https://map.naver.com/p/entry/place/1825758697?c=15.00,0,0,0,dh",
      "summary": "애객러 무릎어깨님 추천 곱창 맛집",
      "tags": [
        "술안주",
        "한식"
      ],
      "navermapurl": "https://map.naver.com/p/search/하남양곱창 본점?c=14,127.2040007,37.5422631,0,dh",
      "review_star": null,
      "review_img": [],
      "review_url": ""
    },
    {
      "name": "족발당",
      "location": "경기 하남시 미사강변한강로 2903",
      "link": "https://map.naver.com/p/search/%EC%A1%B1%EB%B0%9C%EB%8B%B9/place/1885173956?c=15.00,0,0,0,dh&placePath=%3Fentry%253Dbmp",
      "summary": "애객러 무릎어깨님 추천 족발 맛집",
      "tags": [
        "한식"
      ],
      "navermapurl": "https://map.naver.com/p/search/족발당",
      "review_star": null,
      "review_img": [],
      "review_url": ""
    },
    {
      "name": "송돗골 하남직영점",
      "location": "경기 하남시 덕풍북로 14 1층",
      "link": "https://map.naver.com/p/entry/place/1175005334?c=15.00,0,0,0,dh",
      "summary": "애객러 무릎어깨님 추천 육개장 맛집",
      "tags": [
        "한식"
      ],
      "navermapurl": "https://map.naver.com/p/search/송돗골 하남직영점?c=14,127.1987111,37.5475703,0,dh",
      "review_star": null,
      "review_img": [],
      "review_url": ""
    },
    {
      "name": "어부의 술상",
      "location": "경기 하남시 신장1로 36 1층 101호",
      "link": "https://map.naver.com/p/entry/place/1560947450?placePath=%2Fhome&c=15.00,0,0,0,dh",
      "summary": "애객러 무릎어깨님 추천 생선회 맛집",
      "tags": [
        "술안주"
      ],
      "navermapurl": "https://map.naver.com/p/search/어부의 술상?c=14,127.2109489,37.5391469,0,dh",
      "review_star": null,
      "review_img": [],
      "review_url": ""
    },
    {
      "name": "산아래 우렁쌈정식",
      "location": "경기 하남시 감이남로40번길 4722",
      "link": "https://map.naver.com/p/entry/place/1367268788?c=15.00,0,0,0,dh",
      "summary": "애객러 777님 추천 우렁쌈정식 맛집",
      "tags": [
        "한식"
      ],
      "navermapurl": "https://map.naver.com/p/search/산아래 우렁쌈정식",
      "review_star": null,
      "review_img": [],
      "review_url": ""
    }
  ]
}